unit_20211106_1.py
u20211106-0.1.dist-info/METADATA
u20211106-0.1.dist-info/WHEEL
u20211106-0.1.dist-info/top_level.txt
u20211106-0.1.dist-info/RECORD
