Metadata-Version: 2.1
Name: u20211106
Version: 0.1
Summary: d3
Home-page: UNKNOWN
Author: d3
Author-email: u20211106@d3.com
License: UNKNOWN
Platform: UNKNOWN
